figure_manager
