Metadata-Version: 2.1
Name: figure-manager
Version: 0.1.4
Summary: Easily snap Matplotlib figures to suitable location on screen.
Home-page: https://github.com/NorthGuard/figure_manager
Author: Jeppe Nørregaard
Author-email: northguard_serve@tutanota.com
License: MIT License
Keywords: matplotlib figure monitor screen
Platform: UNKNOWN
Classifier: Programming Language :: Python :: 3
Requires-Python: >=3.0
